setup.cfg
setup.py
github_trending.egg-info/PKG-INFO
github_trending.egg-info/SOURCES.txt
github_trending.egg-info/dependency_links.txt
github_trending.egg-info/entry_points.txt
github_trending.egg-info/requires.txt
github_trending.egg-info/top_level.txt
githubtrending/__init__.py
githubtrending/helpers.py
githubtrending/trending.py