Metadata-Version: 1.1
Name: github-trending
Version: 1.0
Summary: Trending repos and developers on Github
Home-page: https://github.com/staranjeet/github-trending-cli
Author: Taranjeet Singh
Author-email: reachtotj@gmail.com
License: MIT
Keywords: github trending repo now developers trending-repo
Platform: UNKNOWN
Classifier: Development Status :: 3 - Alpha
Classifier: Environment :: Console
Classifier: Intended Audience :: Developers
Classifier: Intended Audience :: Information Technology
Classifier: Natural Language :: English
Classifier: Topic :: Software Development :: Build Tools
Classifier: License :: OSI Approved :: MIT License
Classifier: Programming Language :: Python :: 2
Classifier: Programming Language :: Python :: 2.6
Classifier: Programming Language :: Python :: 2.7
